CHANGES.rst
MANIFEST.in
README.rst
setup.py
docs/LICENSE.GPL
docs/LICENSE.txt
src/imio/__init__.py
src/imio.dataexchange.db.egg-info/PKG-INFO
src/imio.dataexchange.db.egg-info/SOURCES.txt
src/imio.dataexchange.db.egg-info/dependency_links.txt
src/imio.dataexchange.db.egg-info/entry_points.txt
src/imio.dataexchange.db.egg-info/namespace_packages.txt
src/imio.dataexchange.db.egg-info/not-zip-safe
src/imio.dataexchange.db.egg-info/requires.txt
src/imio.dataexchange.db.egg-info/top_level.txt
src/imio/dataexchange/__init__.py
src/imio/dataexchange/db/__init__.py
src/imio/dataexchange/db/base.py
src/imio/dataexchange/db/mappers/__init__.py
src/imio/dataexchange/db/mappers/file.py
src/imio/dataexchange/db/mappers/file_type.py
src/imio/dataexchange/db/mappers/request.py
src/imio/dataexchange/db/mappers/router.py
src/imio/dataexchange/db/scripts/__init__.py
src/imio/dataexchange/db/scripts/db.sql
src/imio/dataexchange/db/scripts/init_db.py