Metadata-Version: 1.1
Name: imio.dataexchange.db
Version: 0.4.1
Summary: UNKNOWN
Home-page: https://github.com/imio/
Author: IMIO
Author-email: support@imio.be
License: GPL
Platform: UNKNOWN
Classifier: Programming Language :: Python
